my_happy_python_utils/__init__.py
my_happy_python_utils/async_file_utils.py
my_happy_python_utils/async_shell_utils.py
my_happy_python_utils/color_utils.py
my_happy_python_utils/date_time_utils.py
my_happy_python_utils/json_utils.py
my_happy_python_utils/path_utils.py
my_happy_python_utils/retry_utils.py
my_happy_python_utils/shellUtils.py
my_happy_python_utils/string_utils.py
my_happy_python_utils/version.py
my_happy_python_utils-0.0.45.dist-info/METADATA
my_happy_python_utils-0.0.45.dist-info/WHEEL
my_happy_python_utils-0.0.45.dist-info/top_level.txt
my_happy_python_utils-0.0.45.dist-info/RECORD
